README.rst
setup.py
omr/__init__.py
omr/exam.py
omr/exam_group.py
omr/forms.py
omr/forms.yaml
omr/gui.py
omr/omrcmd.py
omr.egg-info/PKG-INFO
omr.egg-info/SOURCES.txt
omr.egg-info/dependency_links.txt
omr.egg-info/requires.txt
omr.egg-info/top_level.txt
test_omr/__init__.py
test_omr/test_omr.py