Metadata-Version: 1.0
Name: omr
Version: 0.0.7
Summary: Bubble Vision: Optical Mark Reader
Home-page: http://github.com/GregoryCMiller/omr
Author: Greg Miller
Author-email: gmill002@gmail.com
License: UNKNOWN
Platform: UNKNOWN
Classifier: Operating System :: OS Independent
Classifier: Programming Language :: Python
Classifier: Programming Language :: Python :: 2
Classifier: Programming Language :: Python :: 2.7
Classifier: Topic :: Scientific/Engineering :: Image Recognition
Classifier: Topic :: Education :: Testing
